airflow_laminar/__init__.py
airflow_laminar/tests/test_all.py
airflow_laminar-1.16.4.dist-info/METADATA
airflow_laminar-1.16.4.dist-info/WHEEL
airflow_laminar-1.16.4.dist-info/licenses/LICENSE
airflow_laminar-1.16.4.dist-info/RECORD
