Metadata-Version: 2.4
Name: airflow-laminar
Version: 1.16.4
Summary: Meta-repository for airflow-laminar tools
Project-URL: Repository, https://github.com/airflow-laminar/airflow-laminar
Project-URL: Homepage, https://github.com/airflow-laminar/airflow-laminar
Author-email: the airflow-laminar authors <t.paine154@gmail.com>
License: Apache-2.0
License-File: LICENSE
Keywords: airflow,scheduler
Classifier: Development Status :: 4 - Beta
Classifier: Programming Language :: Python
Classifier: Programming Language :: Python :: 3
Classifier: Programming Language :: Python :: 3.11
Classifier: Programming Language :: Python :: 3.12
Classifier: Programming Language :: Python :: 3.13
Classifier: Programming Language :: Python :: 3.14
Classifier: Programming Language :: Python :: Implementation :: CPython
Classifier: Programming Language :: Python :: Implementation :: PyPy
Requires-Python: >=3.11
Requires-Dist: airflow-balancer<0.8,>=0.7.7
Requires-Dist: airflow-common<0.8,>=0.7.7
Requires-Dist: airflow-config<1.12,>=1.11
Requires-Dist: airflow-ha<1.7,>=1.6.2
Requires-Dist: airflow-priority<1.7,>=1.6.1
Requires-Dist: airflow-pydantic<1.6,>=1.5.8
Requires-Dist: airflow-supervisor<1.11,>=1.10.2
Requires-Dist: supervisor-pydantic<1.4,>=1.3.3
Provides-Extra: develop
Requires-Dist: build; extra == 'develop'
Requires-Dist: bump-my-version; extra == 'develop'
Requires-Dist: check-manifest; extra == 'develop'
Requires-Dist: codespell<2.5,>=2.4; extra == 'develop'
Requires-Dist: hatchling; extra == 'develop'
Requires-Dist: mdformat-tables>=1; extra == 'develop'
Requires-Dist: mdformat<1.1,>=0.7.22; extra == 'develop'
Requires-Dist: pytest; extra == 'develop'
Requires-Dist: pytest-cov; extra == 'develop'
Requires-Dist: ruff<0.15,>=0.9; extra == 'develop'
Requires-Dist: twine; extra == 'develop'
Requires-Dist: uv; extra == 'develop'
Requires-Dist: wheel; extra == 'develop'
